{
    "312c2518aaaa70bf76ccbe2b719c51e93d46bc50": {
        "authored_data": "2009 Oct 01 22:44",
        "commit.message": "FIX: SearchEngine.listModules returns MRID without extra attributes (IVY-1128) (thanks to Michael Scheetz)\n\ngit-svn-id: https://svn.apache.org/repos/asf/ant/ivy/core/trunk@820829 13f79535-47bb-0310-9956-ffa450edef68\n",
        "commit.author.name": "Maarten Coene",
        "pcid": "771f3bd0fcdde9bb5b7aa760adfead2d5da7a43c",
        "changes": {
            "src/java/org/apache/ivy/core/search/SearchEngine.java": {
                "old": {
                    "('org.apache.ivy.core.search#SearchEngine', 'listModules(ModuleRevisionId,PatternMatcher)')": [
                        236,
                        237,
                        238,
                        239,
                        249
                    ],
                    "('org.apache.ivy.core.search#SearchEngine', 'listModules(DependencyResolver,ModuleRevisionId,PatternMatcher)')": [
                        277,
                        278,
                        279,
                        288,
                        289
                    ]
                },
                "new": {
                    "('org.apache.ivy.core.search#SearchEngine', 'listModules(ModuleRevisionId,PatternMatcher)')": [
                        236,
                        237,
                        238,
                        248,
                        249,
                        250,
                        251,
                        252,
                        253,
                        254,
                        255,
                        256,
                        257,
                        258,
                        259,
                        260,
                        261,
                        262,
                        263,
                        264,
                        265
                    ],
                    "('org.apache.ivy.core.search#SearchEngine', 'listModules(DependencyResolver,ModuleRevisionId,PatternMatcher)')": [
                        293,
                        294,
                        303,
                        304,
                        305,
                        306,
                        307,
                        308,
                        309,
                        310,
                        311,
                        312,
                        313,
                        314,
                        315,
                        316,
                        317,
                        318,
                        319,
                        320,
                        321
                    ]
                }
            },
            "test/java/org/apache/ivy/core/search/SearchTest.java": {
                "new": {
                    "(None, None)": [
                        21,
                        22,
                        32,
                        33,
                        34,
                        92
                    ],
                    "('org.apache.ivy.core.search#SearchTest', None)": [
                        66
                    ],
                    "('org.apache.ivy.core.search#SearchTest', 'testListModulesWithExtraAttributes')": [
                        67,
                        68,
                        69,
                        70,
                        71,
                        72,
                        73,
                        74,
                        75,
                        76,
                        77,
                        78,
                        79,
                        80,
                        81,
                        82,
                        83,
                        84,
                        85,
                        86,
                        87,
                        88,
                        89,
                        90,
                        91
                    ]
                }
            }
        }
    },
    "771f3bd0fcdde9bb5b7aa760adfead2d5da7a43c": {
        "authored_data": "2009 Oct 01 21:54",
        "commit.message": "FIX: IvyBuildNumber non-deterministic behaviour (IVY-1120)\n\ngit-svn-id: https://svn.apache.org/repos/asf/ant/ivy/core/trunk@820818 13f79535-47bb-0310-9956-ffa450edef68\n",
        "commit.author.name": "Maarten Coene",
        "pcid": "8e1addfc56ff9b554bfb00e28ba359db28c075fe",
        "changes": {
            "src/java/org/apache/ivy/ant/IvyBuildNumber.java": {
                "old": {
                    "('org.apache.ivy.ant#IvyBuildNumber', 'doExecute')": [
                        168,
                        169,
                        170
                    ]
                },
                "new": {
                    "('org.apache.ivy.ant#IvyBuildNumber', 'doExecute')": [
                        168,
                        169,
                        170
                    ]
                }
            }
        }
    },
    "8e1addfc56ff9b554bfb00e28ba359db28c075fe": {
        "authored_data": "2009 Oct 01 21:43",
        "commit.message": "FIX: Change spelling of 'occured' to 'occurred' (IVY-1123)\n\ngit-svn-id: https://svn.apache.org/repos/asf/ant/ivy/core/trunk@820811 13f79535-47bb-0310-9956-ffa450edef68\n",
        "commit.author.name": "Maarten Coene",
        "pcid": "d3ecb70f56f0324b490e7d9dd3189c8369e48946",
        "changes": {
            "src/example/multi-project/projects/version/src/version/Version.java": {
                "old": {
                    "('version#Version', 'register(String)')": [
                        43
                    ]
                },
                "new": {
                    "('version#Version', 'register(String)')": [
                        43
                    ]
                }
            },
            "src/java/org/apache/ivy/core/cache/RepositoryCacheManager.java": {
                "old": {
                    "(None, None)": [
                        130
                    ]
                },
                "new": {
                    "(None, None)": [
                        130
                    ]
                }
            },
            "src/java/org/apache/ivy/core/resolve/ResolveEngine.java": {
                "old": {
                    "('org.apache.ivy.core.resolve#ResolveEngine', None)": [
                        465,
                        1012
                    ]
                },
                "new": {
                    "('org.apache.ivy.core.resolve#ResolveEngine', None)": [
                        465,
                        1012
                    ]
                }
            },
            "src/java/org/apache/ivy/plugins/parser/xml/XmlModuleDescriptorParser.java": {
                "old": {
                    "('org.apache.ivy.plugins.parser.xml#XmlModuleDescriptorParser', 'toIvyFile(InputStream,Resource,File,ModuleDescriptor)')": [
                        151
                    ],
                    "('org.apache.ivy.plugins.parser.xml#XmlModuleDescriptorParser', None)": [
                        337
                    ]
                },
                "new": {
                    "('org.apache.ivy.plugins.parser.xml#XmlModuleDescriptorParser', 'toIvyFile(InputStream,Resource,File,ModuleDescriptor)')": [
                        151
                    ],
                    "('org.apache.ivy.plugins.parser.xml#XmlModuleDescriptorParser', None)": [
                        337
                    ]
                }
            },
            "src/java/org/apache/ivy/plugins/parser/xml/XmlModuleDescriptorUpdater.java": {
                "old": {
                    "('org.apache.ivy.plugins.parser.xml#XmlModuleDescriptorUpdater', None)": [
                        554
                    ]
                },
                "new": {
                    "('org.apache.ivy.plugins.parser.xml#XmlModuleDescriptorUpdater', None)": [
                        554
                    ]
                }
            },
            "src/java/org/apache/ivy/plugins/repository/TransferEvent.java": {
                "old": {
                    "('org.apache.ivy.plugins.repository#TransferEvent', None)": [
                        71
                    ]
                },
                "new": {
                    "('org.apache.ivy.plugins.repository#TransferEvent', None)": [
                        71
                    ]
                }
            },
            "src/java/org/apache/ivy/plugins/resolver/ChainResolver.java": {
                "old": {
                    "('org.apache.ivy.plugins.resolver#ChainResolver', 'getDependency(DependencyDescriptor,ResolveData)')": [
                        135,
                        162
                    ]
                },
                "new": {
                    "('org.apache.ivy.plugins.resolver#ChainResolver', 'getDependency(DependencyDescriptor,ResolveData)')": [
                        135,
                        162
                    ]
                }
            },
            "src/java/org/apache/ivy/util/CredentialsUtil.java": {
                "old": {
                    "('org.apache.ivy.util#CredentialsUtil', 'promptCredentials(Credentials,File)')": [
                        118
                    ],
                    "('org.apache.ivy.util#CredentialsUtil', 'loadPassfile(Credentials,File)')": [
                        151
                    ]
                },
                "new": {
                    "('org.apache.ivy.util#CredentialsUtil', 'promptCredentials(Credentials,File)')": [
                        118
                    ],
                    "('org.apache.ivy.util#CredentialsUtil', 'loadPassfile(Credentials,File)')": [
                        151
                    ]
                }
            },
            "src/java/org/apache/ivy/util/PropertiesFile.java": {
                "old": {
                    "('org.apache.ivy.util#PropertiesFile', None)": [
                        43
                    ],
                    "('org.apache.ivy.util#PropertiesFile', 'save')": [
                        65
                    ]
                },
                "new": {
                    "('org.apache.ivy.util#PropertiesFile', None)": [
                        43
                    ],
                    "('org.apache.ivy.util#PropertiesFile', 'save')": [
                        65
                    ]
                }
            }
        }
    },
    "d3ecb70f56f0324b490e7d9dd3189c8369e48946": {
        "authored_data": "2009 Oct 01 21:31",
        "commit.message": "FIX: Ivy deliver fails to replace dynamic revision when using extra attributes (IVY-1111) (thanks to Michael Scheetz)\n\ngit-svn-id: https://svn.apache.org/repos/asf/ant/ivy/core/trunk@820806 13f79535-47bb-0310-9956-ffa450edef68\n",
        "commit.author.name": "Maarten Coene",
        "pcid": "8b57b6e537a9f37b70b769ebd9d6d44130c5c0ad",
        "changes": {
            "src/java/org/apache/ivy/core/module/id/ModuleRevisionId.java": {
                "old": {
                    "('org.apache.ivy.core.module.id#ModuleRevisionId', 'encodeToString')": [
                        277
                    ]
                },
                "new": {
                    "('org.apache.ivy.core.module.id#ModuleRevisionId', 'encodeToString')": [
                        277,
                        278,
                        279,
                        280
                    ]
                }
            }
        }
    },
    "8b57b6e537a9f37b70b769ebd9d6d44130c5c0ad": {
        "authored_data": "2009 Sep 29 22:11",
        "commit.message": "FIX: IbiblioResolver not always correctly configured when using JRE 1.5 (IVY-1124) (thanks to Flavio Coutinho da Costa)\n\ngit-svn-id: https://svn.apache.org/repos/asf/ant/ivy/core/trunk@820106 13f79535-47bb-0310-9956-ffa450edef68\n",
        "commit.author.name": "Maarten Coene",
        "pcid": "929ff9adfe987f7677c276fb7642fa1fafc6a190",
        "changes": {
            "src/java/org/apache/ivy/plugins/resolver/IBiblioResolver.java": {
                "new": {
                    "('org.apache.ivy.plugins.resolver#IBiblioResolver', 'updateWholePattern')": [
                        306,
                        307
                    ]
                }
            }
        }
    },
    "929ff9adfe987f7677c276fb7642fa1fafc6a190": {
        "authored_data": "2009 Sep 25 22:03",
        "commit.message": "Spelling fix\n\ngit-svn-id: https://svn.apache.org/repos/asf/ant/ivy/core/trunk@819042 13f79535-47bb-0310-9956-ffa450edef68\n",
        "commit.author.name": "Maarten Coene",
        "pcid": "3fef1a85b54dac28bdc63dabc84b27be78021cc4",
        "changes": {
            "test/java/org/apache/ivy/plugins/resolver/FileSystemResolverTest.java": {
                "old": {
                    "('org.apache.ivy.plugins.resolver#FileSystemResolverTest', 'testNoRevision')": [
                        341
                    ]
                },
                "new": {
                    "('org.apache.ivy.plugins.resolver#FileSystemResolverTest', 'testNoRevision')": [
                        341
                    ]
                }
            }
        }
    },
    "3fef1a85b54dac28bdc63dabc84b27be78021cc4": {
        "authored_data": "2009 Sep 25 21:53",
        "commit.message": "FIX: VstfpRepository.readResponse uses bad compare logic (IVY-1119) (thanks to Dave Brosius)\n\ngit-svn-id: https://svn.apache.org/repos/asf/ant/ivy/core/trunk@819038 13f79535-47bb-0310-9956-ffa450edef68\n",
        "commit.author.name": "Maarten Coene",
        "pcid": "19cdfee2eb82d2d0eb911e49652abae7fefb8bb6",
        "changes": {
            "src/java/org/apache/ivy/plugins/repository/vsftp/VsftpRepository.java": {
                "old": {
                    "('org.apache.ivy.plugins.repository.vsftp#VsftpRepository', 'readResponse(boolean,long)')": [
                        468
                    ]
                },
                "new": {
                    "('org.apache.ivy.plugins.repository.vsftp#VsftpRepository', 'readResponse(boolean,long)')": [
                        468
                    ]
                }
            }
        }
    },
    "19cdfee2eb82d2d0eb911e49652abae7fefb8bb6": {
        "authored_data": "2009 Sep 06 08:37",
        "commit.message": "clean format using local variable\n\ngit-svn-id: https://svn.apache.org/repos/asf/ant/ivy/core/trunk@811778 13f79535-47bb-0310-9956-ffa450edef68\n",
        "commit.author.name": "Scokart Gilles",
        "pcid": "d46e1045cc06baa638a32aab5dcd2aeed1c0f890",
        "changes": {
            "src/java/org/apache/ivy/ant/IvyResolve.java": {
                "old": {
                    "('org.apache.ivy.ant#IvyResolve', 'doExecute')": [
                        262,
                        263,
                        264,
                        265,
                        266,
                        267,
                        268,
                        269,
                        270,
                        271,
                        285,
                        286,
                        287,
                        288,
                        289,
                        290,
                        291,
                        292,
                        293,
                        294,
                        295,
                        296
                    ]
                },
                "new": {
                    "('org.apache.ivy.ant#IvyResolve', 'doExecute')": [
                        262,
                        263,
                        264,
                        265,
                        266,
                        267,
                        268,
                        269,
                        270,
                        284,
                        285,
                        286,
                        287,
                        288,
                        289
                    ]
                }
            }
        }
    },
    "d46e1045cc06baa638a32aab5dcd2aeed1c0f890": {
        "authored_data": "2009 Sep 05 15:25",
        "commit.message": "Add documentation and unit test for (IVY-1021)\n\ngit-svn-id: https://svn.apache.org/repos/asf/ant/ivy/core/trunk@811665 13f79535-47bb-0310-9956-ffa450edef68\n",
        "commit.author.name": "Scokart Gilles",
        "pcid": "75c5058e0ba627cf2b3beb849e8baf18190c15d5",
        "changes": {
            "test/java/org/apache/ivy/ant/IvyInstallTest.java": {
                "new": {
                    "('org.apache.ivy.ant#IvyInstallTest', 'testInstallWithAnyType')": [
                        87,
                        88,
                        89,
                        90,
                        91,
                        92,
                        93,
                        94,
                        95,
                        96,
                        97,
                        98
                    ],
                    "('org.apache.ivy.ant#IvyInstallTest', None)": [
                        99,
                        100,
                        113,
                        114,
                        127,
                        128
                    ],
                    "('org.apache.ivy.ant#IvyInstallTest', 'testInstallWithMultipleType')": [
                        101,
                        102,
                        103,
                        104,
                        105,
                        106,
                        107,
                        108,
                        109,
                        110,
                        111,
                        112
                    ],
                    "('org.apache.ivy.ant#IvyInstallTest', 'testInstallWithUnusedType')": [
                        115,
                        116,
                        117,
                        118,
                        119,
                        120,
                        121,
                        122,
                        123,
                        124,
                        125,
                        126
                    ]
                }
            }
        }
    },
    "75c5058e0ba627cf2b3beb849e8baf18190c15d5": {
        "authored_data": "2009 Sep 05 15:22",
        "commit.message": "Trace a message when a property file referenced from the settings doesn't exixts (IVY-1074)\n\ngit-svn-id: https://svn.apache.org/repos/asf/ant/ivy/core/trunk@811664 13f79535-47bb-0310-9956-ffa450edef68\n",
        "commit.author.name": "Scokart Gilles",
        "pcid": "0f5873604eb5da255d96ce3a93de79972ef9d071",
        "changes": {
            "src/java/org/apache/ivy/core/settings/XmlSettingsParser.java": {
                "old": {
                    "('org.apache.ivy.core.settings#XmlSettingsParser', 'propertiesStarted(Map)')": [
                        475
                    ]
                },
                "new": {
                    "('org.apache.ivy.core.settings#XmlSettingsParser', 'propertiesStarted(Map)')": [
                        475
                    ]
                }
            }
        }
    }
}