{
    "f06d54344383a8b1a2d9ad2c7400259b5da11ce7": {
        "authored_data": "2010 Oct 14 21:19",
        "commit.message": "Remove unused import\n\ngit-svn-id: https://svn.apache.org/repos/asf/commons/proper/io/trunk@1022718 13f79535-47bb-0310-9956-ffa450edef68\n",
        "commit.author.name": "Niall Pemberton",
        "pcid": "e07acbbff9fa0706298401441a123a01da112cc7",
        "changes": {
            "src/test/java/org/apache/commons/io/LineIteratorTestCase.java": {
                "old": {
                    "(None, None)": [
                        32
                    ]
                }
            }
        }
    },
    "e07acbbff9fa0706298401441a123a01da112cc7": {
        "authored_data": "2010 Oct 14 00:55",
        "commit.message": "IO-252 Add test to prove that this is fixed by IO-166\n\ngit-svn-id: https://svn.apache.org/repos/asf/commons/proper/io/trunk@1022336 13f79535-47bb-0310-9956-ffa450edef68\n",
        "commit.author.name": "Niall Pemberton",
        "pcid": "9ec6f62abcf0283ec4d64c85f35e25c7252c0e23",
        "changes": {
            "src/test/java/org/apache/commons/io/FileUtilsTestCase.java": {
                "new": {
                    "('org.apache.commons.io#FileUtilsTestCase', None)": [
                        302,
                        307
                    ],
                    "('org.apache.commons.io#FileUtilsTestCase', 'testToFile5')": [
                        303,
                        304,
                        305,
                        306
                    ]
                }
            }
        }
    },
    "9ec6f62abcf0283ec4d64c85f35e25c7252c0e23": {
        "authored_data": "2010 Oct 13 23:20",
        "commit.message": "Now that we are on Java 5, we can use the Throwable version of the exception constructor and avoid loosing the original exception information.\n\ngit-svn-id: https://svn.apache.org/repos/asf/commons/proper/io/trunk@1022322 13f79535-47bb-0310-9956-ffa450edef68\n",
        "commit.author.name": "Gary D. Gregory",
        "pcid": "709de522737d7d97118560416aad2d4f69a8720d",
        "changes": {
            "src/main/java/org/apache/commons/io/LineIterator.java": {
                "old": {
                    "('org.apache.commons.io#LineIterator', 'hasNext')": [
                        107
                    ]
                },
                "new": {
                    "('org.apache.commons.io#LineIterator', 'hasNext')": [
                        107
                    ]
                }
            }
        }
    },
    "709de522737d7d97118560416aad2d4f69a8720d": {
        "authored_data": "2010 Oct 13 23:18",
        "commit.message": "Improve code coverage.\n\ngit-svn-id: https://svn.apache.org/repos/asf/commons/proper/io/trunk@1022321 13f79535-47bb-0310-9956-ffa450edef68\n",
        "commit.author.name": "Gary D. Gregory",
        "pcid": "5bb5a5e588ef0c2c52f517210df79bf7f5e91708",
        "changes": {
            "src/test/java/org/apache/commons/io/LineIteratorTestCase.java": {
                "old": {
                    "(None, None)": [
                        34
                    ],
                    "('org.apache.commons.io#LineIteratorTestCase', None)": [
                        62,
                        205,
                        206,
                        256,
                        257,
                        303,
                        304,
                        315
                    ],
                    "('org.apache.commons.io#LineIteratorTestCase', 'testMissingFile')": [
                        108,
                        113
                    ],
                    "('org.apache.commons.io#LineIteratorTestCase', 'testValidEncoding')": [
                        125,
                        128
                    ],
                    "('org.apache.commons.io#LineIteratorTestCase', 'testInvalidEncoding')": [
                        147,
                        150,
                        155
                    ],
                    "('org.apache.commons.io#LineIteratorTestCase', 'testNextOnly')": [
                        167,
                        170
                    ],
                    "('org.apache.commons.io#LineIteratorTestCase', 'testNextLineOnly')": [
                        188,
                        191
                    ],
                    "('org.apache.commons.io#LineIteratorTestCase', 'testCloseEarly')": [
                        210,
                        213,
                        219,
                        235
                    ],
                    "('org.apache.commons.io#LineIteratorTestCase', 'doTestFileWithSpecifiedLines(int)')": [
                        261,
                        265,
                        274,
                        283
                    ],
                    "('org.apache.commons.io#LineIteratorTestCase', 'testFiltering(List,Reader)')": [
                        353,
                        369
                    ]
                },
                "new": {
                    "(None, None)": [
                        23,
                        32,
                        36
                    ],
                    "('org.apache.commons.io#LineIteratorTestCase', None)": [
                        64,
                        186,
                        187,
                        198,
                        199,
                        200,
                        201,
                        202,
                        203,
                        225,
                        275,
                        321,
                        332
                    ],
                    "('org.apache.commons.io#LineIteratorTestCase', 'testMissingFile')": [
                        110,
                        115
                    ],
                    "('org.apache.commons.io#LineIteratorTestCase', 'testValidEncoding')": [
                        127,
                        130
                    ],
                    "('org.apache.commons.io#LineIteratorTestCase', 'testInvalidEncoding')": [
                        149,
                        152,
                        157
                    ],
                    "('org.apache.commons.io#LineIteratorTestCase', 'testNextOnly')": [
                        169,
                        172
                    ],
                    "('org.apache.commons.io#LineIteratorTestCase', 'testNextWithException')": [
                        188,
                        189,
                        190,
                        191,
                        192,
                        193,
                        194,
                        195,
                        196,
                        197
                    ],
                    "('org.apache.commons.io#LineIteratorTestCase', 'testNextLineOnly')": [
                        208,
                        211
                    ],
                    "('org.apache.commons.io#LineIteratorTestCase', 'testCloseEarly')": [
                        229,
                        232,
                        238,
                        254
                    ],
                    "('org.apache.commons.io#LineIteratorTestCase', 'doTestFileWithSpecifiedLines(int)')": [
                        279,
                        283,
                        292,
                        301
                    ],
                    "('org.apache.commons.io#LineIteratorTestCase', 'testFiltering(List,Reader)')": [
                        370,
                        386
                    ]
                }
            }
        }
    },
    "5bb5a5e588ef0c2c52f517210df79bf7f5e91708": {
        "authored_data": "2010 Oct 13 22:48",
        "commit.message": "Improve code coverage.\n\ngit-svn-id: https://svn.apache.org/repos/asf/commons/proper/io/trunk@1022317 13f79535-47bb-0310-9956-ffa450edef68\n",
        "commit.author.name": "Gary D. Gregory",
        "pcid": "f2c7194deeaf66ef3c83e24cb3a13236efe68261",
        "changes": {
            "src/test/java/org/apache/commons/io/LineIteratorTestCase.java": {
                "old": {
                    "('org.apache.commons.io#LineIteratorTestCase', 'testFiltering')": [
                        314,
                        315,
                        316,
                        320
                    ]
                },
                "new": {
                    "(None, None)": [
                        19,
                        24
                    ],
                    "('org.apache.commons.io#LineIteratorTestCase', 'testFilteringFileReader')": [
                        316,
                        317,
                        318,
                        322,
                        324
                    ],
                    "('org.apache.commons.io#LineIteratorTestCase', None)": [
                        325,
                        326,
                        336,
                        337
                    ],
                    "('org.apache.commons.io#LineIteratorTestCase', 'testFilteringBufferedReader')": [
                        327,
                        328,
                        329,
                        330,
                        331,
                        332,
                        333,
                        334,
                        335
                    ],
                    "('org.apache.commons.io#LineIteratorTestCase', 'testFiltering(List,Reader)')": [
                        338
                    ]
                }
            }
        }
    },
    "f2c7194deeaf66ef3c83e24cb3a13236efe68261": {
        "authored_data": "2010 Oct 13 22:08",
        "commit.message": "Rename to FilerAlteration*\n\ngit-svn-id: https://svn.apache.org/repos/asf/commons/proper/io/trunk@1022311 13f79535-47bb-0310-9956-ffa450edef68\n",
        "commit.author.name": "Niall Pemberton",
        "pcid": "9a1f3f7593406baba3a7fb5a01b2f3b622d53931",
        "changes": {
            "src/main/java/org/apache/commons/io/monitor/FileEntry.java": {
                "old": {
                    "(None, None)": [
                        39
                    ],
                    "('org.apache.commons.io.monitor#FileEntry', 'getChildren')": [
                        152
                    ]
                },
                "new": {
                    "(None, None)": [
                        39
                    ],
                    "('org.apache.commons.io.monitor#FileEntry', 'getChildren')": [
                        152
                    ]
                }
            },
            "src/test/java/org/apache/commons/io/monitor/AbstractMonitorTestCase.java": {
                "old": {
                    "(None, None)": [
                        30
                    ],
                    "('org.apache.commons.io.monitor#AbstractMonitorTestCase', None)": [
                        35,
                        81
                    ],
                    "('org.apache.commons.io.monitor#AbstractMonitorTestCase', 'createObserver(File,FileFilter)')": [
                        87
                    ]
                },
                "new": {
                    "(None, None)": [
                        30
                    ],
                    "('org.apache.commons.io.monitor#AbstractMonitorTestCase', None)": [
                        35,
                        81
                    ],
                    "('org.apache.commons.io.monitor#AbstractMonitorTestCase', 'createObserver(File,FileFilter)')": [
                        87
                    ]
                }
            },
            "src/test/java/org/apache/commons/io/monitor/CollectionFileListener.java": {
                "old": {
                    "(None, None)": [
                        25
                    ],
                    "('org.apache.commons.io.monitor#CollectionFileListener', None)": [
                        28
                    ],
                    "('org.apache.commons.io.monitor#CollectionFileListener', 'onStart(FileObserver)')": [
                        52
                    ],
                    "('org.apache.commons.io.monitor#CollectionFileListener', 'onStop(FileObserver)')": [
                        183
                    ]
                },
                "new": {
                    "(None, None)": [
                        25
                    ],
                    "('org.apache.commons.io.monitor#CollectionFileListener', None)": [
                        28
                    ],
                    "('org.apache.commons.io.monitor#CollectionFileListener', 'onStart(FileAlterationObserver)')": [
                        52
                    ],
                    "('org.apache.commons.io.monitor#CollectionFileListener', 'onStop(FileAlterationObserver)')": [
                        183
                    ]
                }
            }
        }
    },
    "6a60c3a6f28353068dfb21267c0f6048b55f6c13": {
        "authored_data": "2010 Oct 13 03:51",
        "commit.message": "Improve code coverage.\n\ngit-svn-id: https://svn.apache.org/repos/asf/commons/proper/io/trunk@1021989 13f79535-47bb-0310-9956-ffa450edef68\n",
        "commit.author.name": "Gary D. Gregory",
        "pcid": "8698ec2d5196d160c6a888e4346d2790e669f123",
        "changes": {
            "src/test/java/org/apache/commons/io/EndianUtilsTest.java": {
                "new": {
                    "(None, None)": [
                        21
                    ],
                    "('org.apache.commons.io#EndianUtilsTest', None)": [
                        33,
                        34,
                        37,
                        38,
                        39,
                        45,
                        46,
                        47
                    ],
                    "('org.apache.commons.io#EndianUtilsTest', 'testCtor')": [
                        35,
                        36
                    ],
                    "('org.apache.commons.io#EndianUtilsTest', 'testEOFException')": [
                        40,
                        41,
                        42,
                        43,
                        44
                    ]
                }
            }
        }
    },
    "8698ec2d5196d160c6a888e4346d2790e669f123": {
        "authored_data": "2010 Oct 13 03:37",
        "commit.message": "Even though CopyUtils is deprecated, bring it to 100% code coverage.\n\ngit-svn-id: https://svn.apache.org/repos/asf/commons/proper/io/trunk@1021986 13f79535-47bb-0310-9956-ffa450edef68\n",
        "commit.author.name": "Gary D. Gregory",
        "pcid": "2ee073f3eb5da25c88e184ea78581b297f168a06",
        "changes": {
            "src/test/java/org/apache/commons/io/CopyUtilsTest.java": {
                "new": {
                    "(None, None)": [
                        23
                    ],
                    "('org.apache.commons.io#CopyUtilsTest', 'testCtor')": [
                        77,
                        78
                    ],
                    "('org.apache.commons.io#CopyUtilsTest', None)": [
                        79,
                        80,
                        81,
                        110,
                        111,
                        141,
                        142
                    ],
                    "('org.apache.commons.io#CopyUtilsTest', 'testCopy_byteArrayToWriterWithEncoding')": [
                        104,
                        105,
                        106,
                        107,
                        108,
                        109
                    ],
                    "('org.apache.commons.io#CopyUtilsTest', 'testCopy_inputStreamToWriterWithEncoding')": [
                        143,
                        144,
                        145,
                        146,
                        147,
                        148
                    ]
                }
            }
        }
    },
    "2ee073f3eb5da25c88e184ea78581b297f168a06": {
        "authored_data": "2010 Oct 12 19:27",
        "commit.message": "IO-132 Rename FilesystemEntry/Listener/Observer to FilesEntry/Listener/Observer\n\ngit-svn-id: https://svn.apache.org/repos/asf/commons/proper/io/trunk@1021892 13f79535-47bb-0310-9956-ffa450edef68\n",
        "commit.author.name": "Niall Pemberton",
        "pcid": "f04a6d47557933a7fb855c1646c350c856def37d",
        "changes": {
            "src/test/java/org/apache/commons/io/monitor/AbstractMonitorTestCase.java": {
                "old": {
                    "(None, None)": [
                        30
                    ],
                    "('org.apache.commons.io.monitor#AbstractMonitorTestCase', None)": [
                        34,
                        35,
                        38,
                        81
                    ],
                    "('org.apache.commons.io.monitor#AbstractMonitorTestCase', 'createObserver(File,FileFilter)')": [
                        87
                    ]
                },
                "new": {
                    "(None, None)": [
                        30
                    ],
                    "('org.apache.commons.io.monitor#AbstractMonitorTestCase', None)": [
                        34,
                        35,
                        38,
                        81
                    ],
                    "('org.apache.commons.io.monitor#AbstractMonitorTestCase', 'createObserver(File,FileFilter)')": [
                        87
                    ]
                }
            }
        }
    }
}